[
    {
        "title":"child rights",
        "description":"Every child deserves a voice, a future, and a childhood full of hope. Protect their rights — empower their tomorrow.",
        "image": "https://images.unsplash.com/photo-1638768505959-6fc9d8c86c4b?w=600&auto=format&fit=crop&q=60"
    },
    {
        "title":"child rights",
        "description":"Every child deserves a voice, a future, and a childhood full of hope. Protect their rights — empower their tomorrow.",
        "image": "https://images.unsplash.com/photo-1638768505959-6fc9d8c86c4b?w=600&auto=format&fit=crop&q=60"
    },
    {
        "title":"child rights",
        "description":"Every child deserves a voice, a future, and a childhood full of hope. Protect their rights — empower their tomorrow.",
        "image": "https://images.unsplash.com/photo-1638768505959-6fc9d8c86c4b?w=600&auto=format&fit=crop&q=60"
    },
    {
        "title":"child rights",
        "description":"Every child deserves a voice, a future, and a childhood full of hope. Protect their rights — empower their tomorrow.",
        "image": "https://images.unsplash.com/photo-1638768505959-6fc9d8c86c4b?w=600&auto=format&fit=crop&q=60"
    }
]